sinetstream_cli/__main__.py
sinetstream_cli/sinetstream_cli.py
sinetstream_cli-1.9.2.dist-info/METADATA
sinetstream_cli-1.9.2.dist-info/WHEEL
sinetstream_cli-1.9.2.dist-info/entry_points.txt
sinetstream_cli-1.9.2.dist-info/top_level.txt
sinetstream_cli-1.9.2.dist-info/RECORD
