Metadata-Version: 2.4
Name: sinetstream_cli
Version: 1.9.2
Summary: SINETStream Command Line Interface
License: Apache License, Version 2.0
Project-URL: homepage, https://github.com/nii-gakunin-cloud/sinetstream/tree/main/python/sample/cli
Project-URL: repository, https://github.com/nii-gakunin-cloud/sinetstream
Classifier: License :: OSI Approved :: Apache Software License
Classifier: Intended Audience :: Developers
Classifier: Programming Language :: Python :: 3 :: Only
Classifier: Environment :: Console
Requires-Python: >=3.9
Requires-Dist: sinetstream>=1.9.2
Requires-Dist: sinetstream-kafka>=1.9.2
Requires-Dist: sinetstream-mqtt>=1.9.2
Requires-Dist: sinetstream-s3>=1.9.2
